pyowlet/PyOwlet.py
pyowlet/__init__.py
pyowlet-1.0.3.dist-info/LICENSE
pyowlet-1.0.3.dist-info/METADATA
pyowlet-1.0.3.dist-info/WHEEL
pyowlet-1.0.3.dist-info/top_level.txt
pyowlet-1.0.3.dist-info/RECORD
